LICENSE
python_datastructures/__init__.py
python_datastructures/binarySearchTree.py
python_datastructures/circularList.py
python_datastructures/dequeue.py
python_datastructures/doublylinkedlist.py
python_datastructures/heap.py
python_datastructures/linkedlist.py
python_datastructures/queue.py
python_datastructures/stack.py
python_datastructures/trie.py
python_datastructures-0.1.3.dist-info/LICENSE
python_datastructures-0.1.3.dist-info/WHEEL
python_datastructures-0.1.3.dist-info/METADATA
python_datastructures-0.1.3.dist-info/RECORD
