Metadata-Version: 2.1
Name: python-datastructures
Version: 0.1.3
Summary: Python datastructures package
Home-page: https://github.com/TuTomasz/Python-Datastructures
License: MIT
Keywords: Datastructures,Data Structures,queue,stack,trie,heap,linked-list
Author: Tomasz Turek
Author-email: ttomaszito@gmail.com
Requires-Python: >=3.7,<4.0
Classifier: License :: OSI Approved :: MIT License
Classifier: Operating System :: OS Independent
Classifier: Programming Language :: Python :: 3
Classifier: Programming Language :: Python :: 3.7
Classifier: Programming Language :: Python :: 3.8
Classifier: Topic :: Software Development :: Documentation
Classifier: Topic :: Software Development :: Libraries :: Python Modules
Project-URL: Repository, https://github.com/TuTomasz/Python-Datastructures
